Metadata-Version: 2.1
Name: odoo10-addon-contract
Version: 10.0.4.3.1
Summary: Contracts Management - Recurring
Home-page: https://github.com/oca/contract
Author: OpenERP SA, Tecnativa, LasLabs, Odoo Community Association (OCA)
Author-email: support@odoo-community.org
License: AGPL-3
Platform: UNKNOWN
Classifier: Programming Language :: Python
Classifier: Framework :: Odoo
Classifier: License :: OSI Approved :: GNU Affero General Public License v3
Requires-Python: ~=2.7
Requires-Dist: odoo (<10.1dev,>=10.0)
